easy_notifyer/__init__.py
easy_notifyer/report.py
easy_notifyer/utils.py
easy_notifyer/clients/__init__.py
easy_notifyer/clients/mailer.py
easy_notifyer/clients/requests.py
easy_notifyer/clients/telegram.py
easy_notifyer/handlers/__init__.py
easy_notifyer/handlers/mailer.py
easy_notifyer/handlers/telegram.py
easy_notifyer-0.2.1.dist-info/LICENSE.txt
easy_notifyer-0.2.1.dist-info/METADATA
easy_notifyer-0.2.1.dist-info/WHEEL
easy_notifyer-0.2.1.dist-info/top_level.txt
easy_notifyer-0.2.1.dist-info/RECORD
