Metadata-Version: 2.1
Name: easy-notifyer
Version: 0.2.1
Summary: Easy bug reporter for small projects. Zero dependencies - download and run. Asyncio support.
Home-page: https://github.com/strpc/easy_notifyer
Author: strpc
License: MIT
Download-URL: https://pypi.python.org/pypi/easy-notifyer
Keywords: easy-notifyer,telegram,mailer,mail-client
Platform: UNKNOWN
Classifier: Programming Language :: Python :: 3
Classifier: License :: OSI Approved :: MIT License
Classifier: Operating System :: OS Independent
Requires-Python: >=3.7, <4
Provides-Extra: all
Requires-Dist: pytest ; extra == 'all'
Requires-Dist: pytest-mock ; extra == 'all'
Requires-Dist: pytest-asyncio ; extra == 'all'
Requires-Dist: pylint ; extra == 'all'
Requires-Dist: flake8 ; extra == 'all'
Requires-Dist: isort ; extra == 'all'
Requires-Dist: bump2version ; extra == 'all'
Requires-Dist: black ; extra == 'all'
Provides-Extra: dev
Requires-Dist: pytest ; extra == 'dev'
Requires-Dist: pytest-mock ; extra == 'dev'
Requires-Dist: pytest-asyncio ; extra == 'dev'
Requires-Dist: pylint ; extra == 'dev'
Requires-Dist: flake8 ; extra == 'dev'
Requires-Dist: isort ; extra == 'dev'
Requires-Dist: bump2version ; extra == 'dev'
Requires-Dist: black ; extra == 'dev'
